cs/taskqueue.py
cs_taskqueue-20250120.dist-info/WHEEL
cs_taskqueue-20250120.dist-info/METADATA
cs_taskqueue-20250120.dist-info/RECORD
