Metadata-Version: 2.3
Name: cs-taskqueue
Version: 20250120
Summary: A general purpose Task and TaskQueue for running tasks with dependencies and failure/retry, potentially in parallel.
Keywords: python3
Author-email: Cameron Simpson <cs@cskk.id.au>
Classifier: Development Status :: 3 - Alpha
Classifier: Programming Language :: Python :: 3
Classifier: Intended Audience :: Developers
Classifier: Operating System :: OS Independent
Classifier: Topic :: Software Development :: Libraries :: Python Modules
Classifier: License :: OSI Approved :: GNU General Public License v3 or later (GPLv3+)
Requires-Dist: cs.deco>=20250103
Requires-Dist: cs.fsm>=20250120
Requires-Dist: cs.gvutils>=20230816
Requires-Dist: cs.logutils>=20241109
Requires-Dist: cs.pfx>=20241208
Requires-Dist: cs.py.func>=20240630
Requires-Dist: cs.queues>=20250103
Requires-Dist: cs.resources>=20250103
Requires-Dist: cs.result>=20250103
Requires-Dist: cs.seq>=20250103
Requires-Dist: cs.threads>=20241005
Requires-Dist: cs.typingutils>=20230331
Requires-Dist: icontract
Requires-Dist: typeguard
Project-URL: MonoRepo Commits, https://bitbucket.org/cameron_simpson/css/commits/branch/main
Project-URL: Monorepo Git Mirror, https://github.com/cameron-simpson/css
Project-URL: Monorepo Hg/Mercurial Mirror, https://hg.sr.ht/~cameron-simpson/css
Project-URL: Source, https://github.com/cameron-simpson/css/blob/main/lib/python/cs/taskqueue.py
